Metadata-Version: 2.4
Name: devservices
Version: 1.2.4
Requires-Python: >=3.11
License-File: LICENSE.md
Requires-Dist: pyyaml
Requires-Dist: sentry-devenv
Requires-Dist: sentry-sdk
Requires-Dist: packaging
Requires-Dist: supervisor
Provides-Extra: dev
Requires-Dist: black; extra == "dev"
Requires-Dist: mypy; extra == "dev"
Requires-Dist: pre-commit; extra == "dev"
Requires-Dist: pytest; extra == "dev"
Requires-Dist: types-PyYAML; extra == "dev"
Dynamic: license-file
